WonderPy/__init__.py
WonderPy/config.py
WonderPy/components/__init__.py
WonderPy/components/wwCommandAccessory.py
WonderPy/components/wwCommandBase.py
WonderPy/components/wwCommandBody.py
WonderPy/components/wwCommandEyering.py
WonderPy/components/wwCommandHead.py
WonderPy/components/wwCommandMedia.py
WonderPy/components/wwCommandMonoLED.py
WonderPy/components/wwCommandPing.py
WonderPy/components/wwCommandRGB.py
WonderPy/components/wwComponentBase.py
WonderPy/components/wwMedia.py
WonderPy/components/wwSensorAccelerometer.py
WonderPy/components/wwSensorAngle.py
WonderPy/components/wwSensorBase.py
WonderPy/components/wwSensorBaseXYZ.py
WonderPy/components/wwSensorBeacon.py
WonderPy/components/wwSensorButton.py
WonderPy/components/wwSensorDistance.py
WonderPy/components/wwSensorGyroscope.py
WonderPy/components/wwSensorMedia.py
WonderPy/components/wwSensorPing.py
WonderPy/components/wwSensorPose.py
WonderPy/components/wwSensorWheel.py
WonderPy/core/__init__.py
WonderPy/core/wwBTLEMgr.py
WonderPy/core/wwCommands.py
WonderPy/core/wwConstants.py
WonderPy/core/wwMain.py
WonderPy/core/wwRobot.py
WonderPy/core/wwSensors.py
WonderPy/lib/WonderWorkshop/osx/libWWHAL.dylib
WonderPy/util/__init__.py
WonderPy/util/wwMath.py
WonderPy/util/wwPath.py
WonderPy/util/wwPinger.py
WonderPy/util/wwSVG.py
WonderPy-0.1.0.dist-info/METADATA
WonderPy-0.1.0.dist-info/RECORD
WonderPy-0.1.0.dist-info/WHEEL
WonderPy-0.1.0.dist-info/top_level.txt
test/__init__.py
test/robotTestUtil.py
test/test_CommandAccessory.py
test/test_CommandBody.py
test/test_CommandHead.py
test/test_SensorAccelerometer.py
test/test_SensorMisc.py
test/test_SensorPose.py
test/test_math.py
