Metadata-Version: 2.1
Name: WonderPy
Version: 0.1.0
Summary: Python API for working with Wonder Workshop robots
Home-page: https://github.com/playi/WonderPy
Author: Orion Elenzil
Author-email: orion@makewonder.com
License: UNKNOWN
Keywords: robots,dash,dot,cue,wonder workshop,robotics,sketchkit
Platform: UNKNOWN
Classifier: Development Status :: 3 - Alpha
Classifier: Environment :: Console
Classifier: Environment :: MacOS X
Classifier: Framework :: Robot Framework
Classifier: Intended Audience :: Developers
Classifier: Intended Audience :: Education
Classifier: Intended Audience :: End Users/Desktop
Classifier: Intended Audience :: Science/Research
Classifier: License :: OSI Approved :: MIT License
Classifier: Operating System :: MacOS
Classifier: Programming Language :: Python :: 2.7
Requires-Dist: mock
Requires-Dist: svgpathtools
Requires-Dist: PyObjC
